LICENSE
MANIFEST.in
README.md
setup.cfg
setup.py
H51.egg-info/PKG-INFO
H51.egg-info/SOURCES.txt
H51.egg-info/dependency_links.txt
H51.egg-info/requires.txt
H51.egg-info/top_level.txt
h51/__init__.py
h51/client.py
h51/exceptions.py
h51/pagination.py
h51/resources.py
h51/analyzers/__init__.py
h51/analyzers/images.py
h51/transforms/__init__.py
h51/transforms/images.py